kfish/__init__.py
kfish-99.0.202502031542.dist-info/LICENSE
kfish-99.0.202502031542.dist-info/METADATA
kfish-99.0.202502031542.dist-info/WHEEL
kfish-99.0.202502031542.dist-info/top_level.txt
kfish-99.0.202502031542.dist-info/RECORD
