Metadata-Version: 2.2
Name: kfish
Version: 99.0.202502031542
Summary: Redfish helper library
Home-page: https://github.com/karmab/kcli/blob/main/extras/kfish.md
Author: Karim Boumedhel
Author-email: karimboumedhel@gmail.com
License: ASL
License-File: LICENSE
Dynamic: author
Dynamic: author-email
Dynamic: description
Dynamic: home-page
Dynamic: license
Dynamic: summary
